aiopyfix/__init__.py
aiopyfix/client_connection.py
aiopyfix/codec.py
aiopyfix/connection.py
aiopyfix/engine.py
aiopyfix/journaler.py
aiopyfix/message.py
aiopyfix/server_connection.py
aiopyfix/session.py
aiopyfix/transaction.py
aiopyfix/FIX44/__init__.py
aiopyfix/FIX44/fixtags.py
aiopyfix/FIX44/messages.py
aiopyfix/FIX44/msgtype.py
aiopyfix-0.4.dist-info/LICENSE
aiopyfix-0.4.dist-info/METADATA
aiopyfix-0.4.dist-info/WHEEL
aiopyfix-0.4.dist-info/top_level.txt
aiopyfix-0.4.dist-info/RECORD
