Metadata-Version: 2.1
Name: aiopyfix
Version: 0.4
Summary: aiopyfix
Home-page: https://github.com/maxtwen/AIOPyFix/
Author: Maksim Afanasevsky
Author-email: maxtwen1@gmail.com
License: UNKNOWN
Download-URL: https://github.com/maxtwen/AIOPyFix/
Platform: UNKNOWN
